aeplab/__init__.py
aeplab-0.0.3.dist-info/LICENSE
aeplab-0.0.3.dist-info/METADATA
aeplab-0.0.3.dist-info/WHEEL
aeplab-0.0.3.dist-info/top_level.txt
aeplab-0.0.3.dist-info/RECORD
