Metadata-Version: 2.1
Name: aeplab
Version: 0.0.3
Summary: A package for AEP Lab
Home-page: https://github.com/pypa/sampleproject
Author: Fuh-Cherng Jeng
Author-email: jeng@ohio.edu
License: UNKNOWN
Project-URL: Bug Tracker, https://github.com/pypa/sampleproject/issues
Platform: UNKNOWN
Classifier: Programming Language :: Python :: 3
Classifier: License :: OSI Approved :: MIT License
Classifier: Operating System :: OS Independent
Requires-Python: >=3.6
License-File: LICENSE
